grammar/grammar.ebnf
sqlast/App.py
sqlast/Cli.py
sqlast/Grammar.py
sqlast/Indenter.py
sqlast/Parser.py
sqlast/Transformer.py
sqlast/Tree.py
sqlast/Version.py
sqlast/__init__.py
sqlast-1.0.0.dist-info/METADATA
sqlast-1.0.0.dist-info/RECORD
sqlast-1.0.0.dist-info/WHEEL
sqlast-1.0.0.dist-info/entry_points.txt
sqlast-1.0.0.dist-info/top_level.txt
