Metadata-Version: 2.1
Name: sqlast
Version: 1.0.0
Summary: An SQL parser that uses LALR for sql parsing
Home-page: https://github.com/Vesuvium/sqlast
Author: Jacopo Cascioli
Author-email: noreply@jacopocascioli.com
License: MIT
Platform: UNKNOWN
Requires-Dist: click (>=6.7)
Requires-Dist: lark-parser (>=0.6.4)
